CHANGES.txt
README.txt
bootstrap.py
buildout.cfg
setup.py
src/zope/__init__.py
src/zope.app.interface.egg-info/PKG-INFO
src/zope.app.interface.egg-info/SOURCES.txt
src/zope.app.interface.egg-info/dependency_links.txt
src/zope.app.interface.egg-info/namespace_packages.txt
src/zope.app.interface.egg-info/not-zip-safe
src/zope.app.interface.egg-info/requires.txt
src/zope.app.interface.egg-info/top_level.txt
src/zope/app/__init__.py
src/zope/app/interface/__init__.py
src/zope/app/interface/configure.zcml
src/zope/app/interface/interfaces.py
src/zope/app/interface/vocabulary.py
src/zope/app/interface/wref.py
src/zope/app/interface/tests/__init__.py
src/zope/app/interface/tests/test_interface.py